onlyinfomain/__init__.py
onlyinfo-0.1.dist-info/LICENSE.txt
onlyinfo-0.1.dist-info/METADATA
onlyinfo-0.1.dist-info/WHEEL
onlyinfo-0.1.dist-info/top_level.txt
onlyinfo-0.1.dist-info/RECORD
