Metadata-Version: 2.1
Name: onlyinfo
Version: 0.1
Summary: Retrieve information from an OnlyFiles link
Home-page: UNKNOWN
Author: y9
Author-email: yasuwrld999@gmail.com
License: UNKNOWN
Platform: UNKNOWN
Classifier: Programming Language :: Python :: 3
Classifier: License :: OSI Approved :: MIT License
Classifier: Operating System :: OS Independent
License-File: LICENSE.txt
